odoo/addons/crm_phonecall_planner/README.rst
odoo/addons/crm_phonecall_planner/__init__.py
odoo/addons/crm_phonecall_planner/__manifest__.py
odoo/addons/crm_phonecall_planner/i18n/am.po
odoo/addons/crm_phonecall_planner/i18n/ar.po
odoo/addons/crm_phonecall_planner/i18n/bg.po
odoo/addons/crm_phonecall_planner/i18n/bs.po
odoo/addons/crm_phonecall_planner/i18n/ca.po
odoo/addons/crm_phonecall_planner/i18n/ca_ES.po
odoo/addons/crm_phonecall_planner/i18n/crm_phonecall_planner.pot
odoo/addons/crm_phonecall_planner/i18n/cs.po
odoo/addons/crm_phonecall_planner/i18n/da.po
odoo/addons/crm_phonecall_planner/i18n/de.po
odoo/addons/crm_phonecall_planner/i18n/el_GR.po
odoo/addons/crm_phonecall_planner/i18n/en_AU.po
odoo/addons/crm_phonecall_planner/i18n/en_GB.po
odoo/addons/crm_phonecall_planner/i18n/es.po
odoo/addons/crm_phonecall_planner/i18n/es_AR.po
odoo/addons/crm_phonecall_planner/i18n/es_CL.po
odoo/addons/crm_phonecall_planner/i18n/es_CO.po
odoo/addons/crm_phonecall_planner/i18n/es_CR.po
odoo/addons/crm_phonecall_planner/i18n/es_DO.po
odoo/addons/crm_phonecall_planner/i18n/es_EC.po
odoo/addons/crm_phonecall_planner/i18n/es_ES.po
odoo/addons/crm_phonecall_planner/i18n/es_MX.po
odoo/addons/crm_phonecall_planner/i18n/es_PE.po
odoo/addons/crm_phonecall_planner/i18n/es_PY.po
odoo/addons/crm_phonecall_planner/i18n/es_VE.po
odoo/addons/crm_phonecall_planner/i18n/et.po
odoo/addons/crm_phonecall_planner/i18n/eu.po
odoo/addons/crm_phonecall_planner/i18n/fa.po
odoo/addons/crm_phonecall_planner/i18n/fi.po
odoo/addons/crm_phonecall_planner/i18n/fr.po
odoo/addons/crm_phonecall_planner/i18n/fr_CA.po
odoo/addons/crm_phonecall_planner/i18n/fr_CH.po
odoo/addons/crm_phonecall_planner/i18n/fr_FR.po
odoo/addons/crm_phonecall_planner/i18n/gl.po
odoo/addons/crm_phonecall_planner/i18n/gl_ES.po
odoo/addons/crm_phonecall_planner/i18n/he.po
odoo/addons/crm_phonecall_planner/i18n/hi.po
odoo/addons/crm_phonecall_planner/i18n/hr.po
odoo/addons/crm_phonecall_planner/i18n/hr_HR.po
odoo11_addon_crm_phonecall_planner-11.0.1.0.0.99.dev13.dist-info/METADATA
odoo11_addon_crm_phonecall_planner-11.0.1.0.0.99.dev13.dist-info/WHEEL
odoo11_addon_crm_phonecall_planner-11.0.1.0.0.99.dev13.dist-info/top_level.txt
odoo11_addon_crm_phonecall_planner-11.0.1.0.0.99.dev13.dist-info/RECORD
